georegression/__init__.py
georegression/ale_utils.py
georegression/distance_utils.py
georegression/kernel.py
georegression/local_ale.py
georegression/local_pd.py
georegression/neighbour_utils.py
georegression/numba_impl.py
georegression/spatial_temporal_moran.py
georegression/stacking_model.py
georegression/weight_matrix.py
georegression/weight_model.py
georegression/simulation/parameter_tuning.py
georegression/simulation/simulation.py
georegression/simulation/simulation_data_fitting.py
georegression/simulation/simulation_for_STST_variation.py
georegression/simulation/simulation_for_ale.py
georegression/simulation/simulation_for_data_size.py
georegression/simulation/simulation_for_fitting.py
georegression/simulation/simulation_for_importance.py
georegression/simulation/simulation_for_robust.py
georegression/simulation/simulation_utils.py
georegression/test/__init__.py
georegression/test/data/EcosystemServicesIndicator.csv
georegression/test/data/HousePrice_Shanghai.csv
georegression/test/data/TOD_weekend.csv
georegression/test/data/TOD_workday.csv
georegression/test/data/__init__.py
georegression/test/efficiency/__init__.py
georegression/test/efficiency/distance_matrix_dask.py
georegression/test/efficiency/distance_matrix_method.py
georegression/test/efficiency/distance_matrix_sort.py
georegression/test/efficiency/numba_inverse.py
georegression/test/efficiency/numba_stack.py
georegression/test/efficiency/regression_model_solver.py
georegression/test/efficiency/regression_numba.py
georegression/test/efficiency/regression_parallel.py
georegression/test/efficiency/second_neighbor_numba.py
georegression/test/efficiency/second_neighbor_operation.py
georegression/test/efficiency/second_neighbour_sparse.py
georegression/test/efficiency/sklearn_intel.py
georegression/test/efficiency/sparse_compatibility.py
georegression/test/efficiency/sparse_numba_compatibility.py
georegression/test/efficiency/sparse_operation.py
georegression/test/efficiency/tree_fit_predict.py
georegression-1.0.2.dist-info/METADATA
georegression-1.0.2.dist-info/WHEEL
georegression-1.0.2.dist-info/licenses/LICENSE
georegression-1.0.2.dist-info/RECORD
