Metadata-Version: 2.4
Name: georegression
Version: 1.0.2
Summary: georegression
Project-URL: Homepage, https://github.com/46319943/GeoRegression
Project-URL: Bug Tracker, https://github.com/46319943/GeoRegression/issues
Author: PiaoYang
License-File: LICENSE
Classifier: License :: OSI Approved :: MIT License
Classifier: Operating System :: OS Independent
Classifier: Programming Language :: Python :: 3
Requires-Python: >=3.7
Requires-Dist: dask
Requires-Dist: hdbscan
Requires-Dist: joblib
Requires-Dist: matplotlib
Requires-Dist: numba
Requires-Dist: numpy
Requires-Dist: pandas
Requires-Dist: plotly
Requires-Dist: scikit-learn
Requires-Dist: scipy
Requires-Dist: slab-utils
Requires-Dist: umap-learn
Requires-Dist: xgboost
